{
	"de":{
		"message":"Hinweis",
		"yes":"Ja",
		"no":"Nein",
		"wizard":"Assistent",
		"more":"Mehr",
		"not-defined":"Not defined",
		"delete":"löschen",
		"new":"Neu",
		"edit":"bearbeiten",
		"list":"Liste",
		"search":"Suche",
		"form":"Formular",
		"action":"Aktion",
		"recreate":"Nachschaffen",
		"latest":"Letzte",
		"next":"nächste",
		"previous":"vorig",
		"step":"Schritt",
		"first":"erste",
		"date":"Datum",
		"remarks":"Anmerkungen",
		"go-back":"geh zurück",
		"ignore":"ignorieren",
		"upload":"Hochladen",
		"installed":"installiert",
		"chart":"Diagramm",
		"message":"Hinweis",
		"update":"Aktualisieren", 
		"upgrade":"Aktualisieren",
		"no-file-chosen":"Keine Datei ausgewählt",
		"export-result":"Export-Ergebnis",
		"download-pdf":"PDF zum Download",
		"add-new":"Neu hinzufügen",
		"data-import":"Datenimport",
	    "users":"Benutzer",
		"administration":"Verwaltung",
	    "translation":"Übersetzung",
	    "dashboard":"Startseite",
	    "settings":"Einstellungen",
	    "preference":"Persönliche Einstellungen",
	    "help":"Hilfe", "note":"Hinweis",
	    "loading":"Verladung",
	    "overview":"Überblick",
	    "options":"Optionen",
	    "loading-data":"Verladung {0}",
		"remove":"Entfernen",
		"description":"Beschreibung",
		"use-administrator-account-to-see-further-information":"Bitte verwenden Sie Administrator-Konto für das Sehen weitere Information",
	    "you-want-to-proceed":"Are you sure you want to proceed ? ",
    	"request-is-being-processed":"Ihre Anfrage wird bearbeitet",
	    "request-is-being-scheduled":"Ihre Anfrage wird geplant ist",
	    "terms-of-service":"Nutzungsbedingungen",
	    "updated":"Aktualisiert", "on":"am", "generated":"erzeugt",
	    "date-added":"Datum hinzugefügt",
	    "x-out-of-y-records":"{0} von {1} Aufzeichnungen.",
	    "x-out-of-y-r":"{0} von {1} {2}.",
	    "search-result-for-data-found-x-results":"Suchergebnis für {0}, gefunden {1} Ergebnisse",
	    "showing-start-end-till-from-x-result":"Zeige {0} bis {1} von {2} Einträgen",
	    "showing-start-end-page-till-from-x-page-result":"Zeige {0} (Seite {2}) von {1} Aufzeichnungen ({3} Seiten)",
	    "no-data-found":"kein {0} gefunden",
	    "no-datas-found":"keine {0} gefunden",
		"some-problem-while-getting-data":"Ein Problem beim Erhalten {0}",
		"some-problem-while-connecting":"Ein Problem beim Anschließen {0}",
		"some-problem-while-updating-the-data":"Einige Probleme beim Aktualisieren {0}",
	    "successfully-updated-the-data":"{0} wurde aktualisiert",
	    "process-finished-successfully-please-proceed-to-next-step-for-further-details":"{0}, gehen Sie bitte zum nächsten Schritt für weitere Details",
	    "process-finished-successfully-but-with-problem":"{0}, Aber wir konnten nicht gehen zu den nächsten Schritten wegen der folgenden Ausgaben"
	}, "en":{
	    "x-out-of-y-records":"{0} out of {1} records.",
	    "x-out-of-y-r":"{0} out of {1} {2}.",
	    "no-data-found":"No {0} found",
	    "no-data-found":"No {0} found",
	    "search-result-for-data-found-x-results":"Search result for {0}, found {1} results",
		 "some-problem-while-getting-data":"Some problem while getting {0}",
		"some-problem-while-updating-data":"Some problem while updating {0}",
		"showing-start-end-page-till-from-x-page-result":"Showing {0} (Page {2}) of {1} records ({3} Pages)",
		"you-want-to-proceed":"Are you sure you want to proceed ? ",
	    "process-finished-successfully-please-proceed-to-next-step-for-further-details":"{0} successfully please proceed to next step for further details"
	}
}