{
	"title":"Simpleportal webserver default resources",
	"id":"simpleportal-webserver-resources",
	"plugintype":"resource",
	"version":"1.0",
	"buildprops":{
		"resource":[
            {
            	"subpath":"./resources/uiplugin/backbone-ext","type":"directory",
            	"files":[
					"backbone-ext"
    	       ]
            },{
            	"subpath":"./resources/plugins/themes/sp-default","type":"directory",
            	"files":[
					"sp-default"
    	       ]
            },{
            	"subpath":"./resources/plugins/webapps/sp-admin","type":"directory",
            	"files":[
					"sp-admin"
    	       ]
            },{
            	"subpath":"./resources/plugins/webapps/sp-config","type":"directory",
            	"files":[
					"sp-config"
    	       ]
            },{
            	"subpath":"./resources/plugins/webapps/sp-langbuilder","type":"directory",
            	"files":[
					"sp-langbuilder"
    	       ]
            },{
            	"subpath":"./resources/plugins/webapps/sp-pluginmanager","type":"directory",
            	"files":[
					"sp-pluginmanager"
    	       ]
            },{
            	"subpath":"./resources/plugins/layouts/bootstrap","type":"directory",
            	"files":[
					"bootstrap-layout"
    	       ]
            },{
            	"subpath":"./resources/public/cdn","type":"directory",
            	"files":[
					"sp-cdn"
    	       ]
            },{
            	"subpath":"./resources/templates","type":"directory",
            	"files":[
					"simpleportal-webserver-templates"
    	       ]
            }
        ]
	}
}